pyteslaapi/BatterySensor.py
pyteslaapi/BinarySensor.py
pyteslaapi/Charger.py
pyteslaapi/DriveSensor.py
pyteslaapi/GPS.py
pyteslaapi/Lock.py
pyteslaapi/__init__.py
pyteslaapi/__main__.py
pyteslaapi/charge.py
pyteslaapi/client.py
pyteslaapi/client.pyc
pyteslaapi/climate.py
pyteslaapi/connection.py
pyteslaapi/controller.py
pyteslaapi/drive.py
pyteslaapi/exceptions.py
pyteslaapi/gui_settings.py
pyteslaapi/vehicle.py
pyteslaapi/__pycache__/charge.cpython-37.pyc
pyteslaapi/__pycache__/client.cpython-37.pyc
pyteslaapi/__pycache__/climate.cpython-37.pyc
pyteslaapi/__pycache__/drive.cpython-37.pyc
pyteslaapi/__pycache__/exceptions.cpython-37.pyc
pyteslaapi/__pycache__/gui_settings.cpython-37.pyc
pyteslaapi/__pycache__/vehicle.cpython-37.pyc
pyteslaapi-0.0.31.dist-info/METADATA
pyteslaapi-0.0.31.dist-info/RECORD
pyteslaapi-0.0.31.dist-info/WHEEL
pyteslaapi-0.0.31.dist-info/top_level.txt
