Metadata-Version: 2.1
Name: pyteslaapi
Version: 0.0.31
Summary: A library to work with Tesla API.
Home-page: https://github.com/tyamell/pyteslaapi
Author: Ty Amell
Author-email: 
License: Apache 2.0
Platform: UNKNOWN
Classifier: Intended Audience :: Developers
Classifier: Operating System :: OS Independent
Classifier: Programming Language :: Python :: 3
Classifier: Programming Language :: Python :: 3.5
Classifier: Programming Language :: Python :: 3.7
Classifier: Topic :: Internet
Requires-Python: >=3
Requires-Dist: requests
